macloudapisdk/__init__.py
macloudapisdk/signer.py
macloudapisdk-1.0.3.dist-info/LICENSE
macloudapisdk-1.0.3.dist-info/METADATA
macloudapisdk-1.0.3.dist-info/WHEEL
macloudapisdk-1.0.3.dist-info/top_level.txt
macloudapisdk-1.0.3.dist-info/RECORD
