Metadata-Version: 2.1
Name: macloudapisdk
Version: 1.0.3
Summary: Api Sdk For Python
Home-page: https://github.com/macloud-api/macloud-python
Author: macloudapisdk
Author-email: macloudapisdk@outlook.com
Classifier: Programming Language :: Python :: 3
Classifier: License :: OSI Approved :: MIT License
Requires-Python: >=3.5
License-File: LICENSE
